pyconject/__init__.py
pyconject/context.py
pyconject/pyconject.py
pyconject/registry.py
pyconject/utils.py
pyconject-0.1.6.dist-info/licenses/LICENSE
pyconject-0.1.6.dist-info/METADATA
pyconject-0.1.6.dist-info/WHEEL
pyconject-0.1.6.dist-info/top_level.txt
pyconject-0.1.6.dist-info/RECORD
