Metadata-Version: 2.4
Name: pyconject
Version: 0.1.6
Summary: pyconject --- a highly opinionated PYthon CONfig inJECTor library.
Author-email: "Edward L." <neolaw+pyconject@gmail.com>
Project-URL: Homepage, https://github.com/neolaw84/pyconject
Project-URL: Issues, https://github.com/neolaw84/pyconject/issues
Classifier: Programming Language :: Python :: 3
Classifier: License :: OSI Approved :: MIT License
Classifier: Operating System :: OS Independent
Requires-Python: >=3.9
License-File: LICENSE
Dynamic: license-file
